ask_sdk_webservice_support/__init__.py
ask_sdk_webservice_support/__version__.py
ask_sdk_webservice_support/py.typed
ask_sdk_webservice_support/verifier.py
ask_sdk_webservice_support/verifier_constants.py
ask_sdk_webservice_support/webservice_handler.py
ask_sdk_webservice_support-1.3.3.dist-info/METADATA
ask_sdk_webservice_support-1.3.3.dist-info/WHEEL
ask_sdk_webservice_support-1.3.3.dist-info/top_level.txt
ask_sdk_webservice_support-1.3.3.dist-info/RECORD
